music_assistant_client/__init__.py
music_assistant_client/client.py
music_assistant_client/config.py
music_assistant_client/connection.py
music_assistant_client/constants.py
music_assistant_client/exceptions.py
music_assistant_client/helpers.py
music_assistant_client/music.py
music_assistant_client/player_queues.py
music_assistant_client/players.py
music_assistant_client/py.typed
music_assistant_client-1.2.4.dist-info/licenses/LICENSE
music_assistant_client-1.2.4.dist-info/METADATA
music_assistant_client-1.2.4.dist-info/WHEEL
music_assistant_client-1.2.4.dist-info/top_level.txt
music_assistant_client-1.2.4.dist-info/RECORD
