Metadata-Version: 2.4
Name: music_assistant_client
Version: 1.2.4
Summary: Music Assistant Client
Author-email: The Music Assistant Authors <music_assistant@users.noreply.github.com>
License: Apache-2.0
Platform: any
Classifier: Environment :: Console
Classifier: Programming Language :: Python :: 3.11
Classifier: Programming Language :: Python :: 3.12
Classifier: Programming Language :: Python :: 3.13
Requires-Python: >=3.11
License-File: LICENSE
Requires-Dist: aiohttp>=3.8.6
Requires-Dist: music_assistant_models==1.1.51
Requires-Dist: orjson>=3.9
Provides-Extra: test
Requires-Dist: codespell==2.4.1; extra == "test"
Requires-Dist: isort==6.0.1; extra == "test"
Requires-Dist: mypy==1.16.1; extra == "test"
Requires-Dist: pre-commit==4.2.0; extra == "test"
Requires-Dist: pre-commit-hooks==5.0.0; extra == "test"
Requires-Dist: tomli==2.2.1; extra == "test"
Requires-Dist: ruff==0.12.1; extra == "test"
Dynamic: license-file
